<?xml version="1.0" encoding="UTF-8"?>
<results title="frequencies">
 <result title="frequency" count="91">Ocepeia</result>
 <result title="frequency" count="68">Dictyostelium</result>
 <result title="frequency" count="50">Macroscelides</result>
 <result title="frequency" count="41">Desmostylus</result>
 <result title="frequency" count="38">Orycteropus</result>
 <result title="frequency" count="37">Chrysochloris</result>
 <result title="frequency" count="30">Eumetopias</result>
 <result title="frequency" count="30">Rhinolophus</result>
 <result title="frequency" count="29">Plesiorycteropus</result>
 <result title="frequency" count="26">Dasypus</result>
 <result title="frequency" count="25">Hemicentetes</result>
 <result title="frequency" count="25">Canis</result>
 <result title="frequency" count="25">Felis</result>
 <result title="frequency" count="24">Bathygenys</result>
 <result title="frequency" count="24">Nycteris</result>
 <result title="frequency" count="24">Ashoroa</result>
 <result title="frequency" count="24">Tursiops</result>
 <result title="frequency" count="23">Paleoparadoxia</result>
 <result title="frequency" count="22">Trichechus</result>
 <result title="frequency" count="22">Atelerix</result>
 <result title="frequency" count="22">Procavia</result>
 <result title="frequency" count="21">Tadarida</result>
 <result title="frequency" count="19">Choloepus</result>
 <result title="frequency" count="19">Lepus</result>
 <result title="frequency" count="19">Equus</result>
 <result title="frequency" count="18">Sorex</result>
 <result title="frequency" count="18">Cavia</result>
 <result title="frequency" count="18">Homo</result>
 <result title="frequency" count="17">Drosophila</result>
 <result title="frequency" count="17">Manis</result>
 <result title="frequency" count="16">Chrysemys</result>
 <result title="frequency" count="16">Didelphis</result>
 <result title="frequency" count="16">Phosphatherium</result>
 <result title="frequency" count="16">Behemotops</result>
 <result title="frequency" count="16">Cambaytherium</result>
 <result title="frequency" count="15">Sylvilagus</result>
 <result title="frequency" count="14">Science</result>
 <result title="frequency" count="12">Macaca</result>
 <result title="frequency" count="12">Pelodiscus</result>
 <result title="frequency" count="11">Pteropus</result>
 <result title="frequency" count="11">Bradypus</result>
 <result title="frequency" count="10">Anthracobune</result>
 <result title="frequency" count="9">Tupaia</result>
 <result title="frequency" count="9">Eritherium</result>
 <result title="frequency" count="9">Radinskya</result>
 <result title="frequency" count="8">Teilhardimys</result>
 <result title="frequency" count="8">Cynocephalus</result>
 <result title="frequency" count="8">Kulbeckia</result>
 <result title="frequency" count="8">Lestodon</result>
 <result title="frequency" count="7">Elephantulus</result>
 <result title="frequency" count="6">Phenacolophus</result>
 <result title="frequency" count="6">Rhipicephalus</result>
 <result title="frequency" count="6">Megatherium</result>
 <result title="frequency" count="6">Tamandua</result>
 <result title="frequency" count="5">Hyopsodus</result>
 <result title="frequency" count="4">Hallensia</result>
 <result title="frequency" count="4">Taeniopygia</result>
 <result title="frequency" count="4">Potamogale</result>
 <result title="frequency" count="4">Gallus</result>
 <result title="frequency" count="4">Rhynchocyon</result>
 <result title="frequency" count="4">Dspp</result>
 <result title="frequency" count="4">Pleuraspidotherium</result>
 <result title="frequency" count="4">Planorbis</result>
 <result title="frequency" count="4">Hippopotamus</result>
 <result title="frequency" count="4">Anas</result>
 <result title="frequency" count="4">Trichostrongylus</result>
 <result title="frequency" count="4">Melopsittacus</result>
 <result title="frequency" count="3">Grns</result>
 <result title="frequency" count="3">Lagidium</result>
 <result title="frequency" count="3">Ptolemaia</result>
 <result title="frequency" count="3">Linognathus</result>
 <result title="frequency" count="3">Meniscotherium</result>
 <result title="frequency" count="3">Alligator</result>
 <result title="frequency" count="3">Tmax</result>
 <result title="frequency" count="3">Chaetophractus</result>
 <result title="frequency" count="3">Eomanis</result>
 <result title="frequency" count="3">Nakusia</result>
 <result title="frequency" count="3">Protungulatum</result>
 <result title="frequency" count="3">Crocuta</result>
 <result title="frequency" count="3">Ateles</result>
 <result title="frequency" count="3">Damalinia</result>
 <result title="frequency" count="3">Numidotherium</result>
 <result title="frequency" count="3">Chambius</result>
 <result title="frequency" count="3">Pilgrimella</result>
 <result title="frequency" count="3">Obergfellia</result>
 <result title="frequency" count="3">Cabassous</result>
 <result title="frequency" count="3">Meleagris</result>
 <result title="frequency" count="3">Utaetus</result>
 <result title="frequency" count="2">Gedoelstia</result>
 <result title="frequency" count="2">Tolypeutes</result>
 <result title="frequency" count="2">Typhlops</result>
 <result title="frequency" count="2">Atta</result>
 <result title="frequency" count="2">Cryptophractus</result>
 <result title="frequency" count="2">Hyaena</result>
 <result title="frequency" count="2">Arctocebus</result>
 <result title="frequency" count="2">Amoebozoa</result>
 <result title="frequency" count="2">Ornithorhynchus</result>
 <result title="frequency" count="2">Chinchilla</result>
 <result title="frequency" count="2">Chaeropus</result>
 <result title="frequency" count="2">Kalitherium</result>
 <result title="frequency" count="2">Zaedyus</result>
 <result title="frequency" count="2">Capsaspora</result>
 <result title="frequency" count="2">Kinkonychelys</result>
 <result title="frequency" count="2">Nothrotheriops</result>
 <result title="frequency" count="2">Zalambdalestes</result>
 <result title="frequency" count="2">Otlestes</result>
 <result title="frequency" count="2">Namatherium</result>
 <result title="frequency" count="2">Mammut</result>
 <result title="frequency" count="2">Paracooperia</result>
 <result title="frequency" count="2">Priodontes</result>
 <result title="frequency" count="2">Gigantocotyle</result>
 <result title="frequency" count="2">Euphractus</result>
 <result title="frequency" count="2">Neospora</result>
 <result title="frequency" count="2">Ukhaatherium</result>
 <result title="frequency" count="2">Dipodomys</result>
 <result title="frequency" count="2">Petrodromus</result>
 <result title="frequency" count="2">Thysaniezia</result>
 <result title="frequency" count="2">Paraceratherium</result>
 <result title="frequency" count="2">Todralestes</result>
 <result title="frequency" count="2">Minchenella</result>
 <result title="frequency" count="2">Besnoitia</result>
 <result title="frequency" count="1">Notostylops</result>
 <result title="frequency" count="1">Heptodon</result>
 <result title="frequency" count="1">Proganochelys</result>
 <result title="frequency" count="1">Deinotherium</result>
 <result title="frequency" count="1">Myorycteropus</result>
 <result title="frequency" count="1">Aphaenogaster</result>
 <result title="frequency" count="1">Hyperoambon</result>
 <result title="frequency" count="1">Myrmecophaga</result>
 <result title="frequency" count="1">Pakicetus</result>
 <result title="frequency" count="1">Lammidhania</result>
 <result title="frequency" count="1">Balanites</result>
 <result title="frequency" count="1">Parvoviridae</result>
 <result title="frequency" count="1">Note</result>
 <result title="frequency" count="1">Oesophagostomum</result>
 <result title="frequency" count="1">Combretum</result>
 <result title="frequency" count="1">Crossover</result>
 <result title="frequency" count="1">Numida</result>
 <result title="frequency" count="1">Ishatherium</result>
 <result title="frequency" count="1">Aardvark</result>
 <result title="frequency" count="1">Haplolambda</result>
 <result title="frequency" count="1">Rhinoceros</result>
 <result title="frequency" count="1">Trichoplax</result>
 <result title="frequency" count="1">Monodelphis</result>
 <result title="frequency" count="1">Setifer</result>
 <result title="frequency" count="1">Eremnochelys</result>
 <result title="frequency" count="1">Food</result>
 <result title="frequency" count="1">Rana</result>
 <result title="frequency" count="1">Lammidhan</result>
 <result title="frequency" count="1">Mutalyzer</result>
 <result title="frequency" count="1">Hsanotherium</result>
 <result title="frequency" count="1">Correct</result>
 <result title="frequency" count="1">Arctocyon</result>
 <result title="frequency" count="1">Neanderthal</result>
 <result title="frequency" count="1">Denisova</result>
 <result title="frequency" count="1">Dugong</result>
 <result title="frequency" count="1">Tricentes</result>
 <result title="frequency" count="1">Brachyteles</result>
 <result title="frequency" count="1">Plateosaurus</result>
 <result title="frequency" count="1">Acromyrmex</result>
 <result title="frequency" count="1">Erinaceus</result>
 <result title="frequency" count="1">Aplysia</result>
 <result title="frequency" count="1">Tachyglossus</result>
 <result title="frequency" count="1">Shantungosaurus</result>
 <result title="frequency" count="1">Echinosorex</result>
 <result title="frequency" count="1">Mapt</result>
 <result title="frequency" count="1">Validated</result>
 <result title="frequency" count="1">Echinococcus</result>
 <result title="frequency" count="1">Cand</result>
 <result title="frequency" count="1">Mesohippus</result>
 <result title="frequency" count="1">Fasciola</result>
 <result title="frequency" count="1">Rhinoestrus</result>
 <result title="frequency" count="1">Apusozoa</result>
 <result title="frequency" count="1">Colobus</result>
 <result title="frequency" count="1">Cardiovirus</result>
 <result title="frequency" count="1">Adapis</result>
 <result title="frequency" count="1">Indobune</result>
 <result title="frequency" count="1">Time</result>
 <result title="frequency" count="1">Phacopsylla</result>
 <result title="frequency" count="1">Circoviridae</result>
 <result title="frequency" count="1">Jaculus</result>
 <result title="frequency" count="1">Holotype</result>
 <result title="frequency" count="1">Jozaria</result>
 <result title="frequency" count="1">Himantura</result>
 <result title="frequency" count="1">Tapirus</result>
 <result title="frequency" count="1">Sciurus</result>
 <result title="frequency" count="1">Schistosoma</result>
 <result title="frequency" count="1">Spiral</result>
 <result title="frequency" count="1">Blaesodactylus</result>
 <result title="frequency" count="1">Probstmayria</result>
 <result title="frequency" count="1">Paschatherium</result>
 <result title="frequency" count="1">Voay</result>
 <result title="frequency" count="1">Evenness</result>
 <result title="frequency" count="1">Grandis</result>
 <result title="frequency" count="1">Miosengi</result>
 <result title="frequency" count="1">Xenopus</result>
 <result title="frequency" count="1">Phocoena</result>
 <result title="frequency" count="1">Lancet</result>
 <result title="frequency" count="1">Avitellina</result>
 <result title="frequency" count="1">Chlamyphorus</result>
 <result title="frequency" count="1">Pusa</result>
 <result title="frequency" count="1">Amphimedon</result>
 <result title="frequency" count="1">Network</result>
 <result title="frequency" count="1">Abronia</result>
 <result title="frequency" count="1">Load</result>
 <result title="frequency" count="1">Physeter</result>
 <result title="frequency" count="1">Kwandala</result>
 <result title="frequency" count="1">Moniezia</result>
 <result title="frequency" count="1">Anopheles</result>
 <result title="frequency" count="1">Yellow</result>
 <result title="frequency" count="1">Glossina</result>
 <result title="frequency" count="1">Strongyloides</result>
 <result title="frequency" count="1">Opuntia</result>
 <result title="frequency" count="1">Inia</result>
 <result title="frequency" count="1">Ambylosomus</result>
 <result title="frequency" count="1">Eimeria</result>
 <result title="frequency" count="1">Zapus</result>
 <result title="frequency" count="1">Stellaluna</result>
 <result title="frequency" count="1">Osirix</result>
 <result title="frequency" count="1">Anoplocephala</result>
 <result title="frequency" count="1">Heterohyrax</result>
 <result title="frequency" count="1">Sarcophilus</result>
 <result title="frequency" count="1">Torneria</result>
 <result title="frequency" count="1">Myorhynchocyon</result>
 <result title="frequency" count="1">Tetraclaenodon</result>
 <result title="frequency" count="1">Ogmocotyle</result>
 <result title="frequency" count="1">Asioryctes</result>
 <result title="frequency" count="1">Neophocaena</result>
 <result title="frequency" count="1">Leptorycteropus</result>
 <result title="frequency" count="1">Mylodon</result>
 <result title="frequency" count="1">Nementchatherium</result>
 <result title="frequency" count="1">Hyrax</result>
 <result title="frequency" count="1">Myrmecaphaga</result>
 <result title="frequency" count="1">Callorhinus</result>
 <result title="frequency" count="1">Family</result>
 <result title="frequency" count="1">Ocepeiidae</result>
 <result title="frequency" count="1">Longistrongylus</result>
 <result title="frequency" count="1">Nesophontes</result>
 <result title="frequency" count="1">Hyomys</result>
 <result title="frequency" count="1">Random</result>
 <result title="frequency" count="1">Coendou</result>
 <result title="frequency" count="1">Dendrohyrax</result>
 <result title="frequency" count="1">Rondeletia</result>
 <result title="frequency" count="1">Monosiga</result>
 <result title="frequency" count="1">Alice</result>
 <result title="frequency" count="1">Mammuthus</result>
 <result title="frequency" count="1">Odontochelys</result>
 <result title="frequency" count="1">Oestrus</result>
 <result title="frequency" count="1">Theileria</result>
 <result title="frequency" count="1">Branchiostoma</result>
 <result title="frequency" count="1">Multidivtime</result>
 <result title="frequency" count="1">Mutation</result>
 <result title="frequency" count="1">Salpingoeca</result>
 <result title="frequency" count="1">Danio</result>
 <result title="frequency" count="1">Herodotius</result>
 <result title="frequency" count="1">Calicophoron</result>
 <result title="frequency" count="1">Nilocotyle</result>
 <result title="frequency" count="1">Haqueina</result>
 <result title="frequency" count="1">Teladorsagia</result>
 <result title="frequency" count="1">Skills</result>
 <result title="frequency" count="1">Palaeanodon</result>
 <result title="frequency" count="1">Lactobacilli</result>
 <result title="frequency" count="1">Herpetocetus</result>
 <result title="frequency" count="1">Tigari</result>
 <result title="frequency" count="1">Ambulocetus</result>
 <result title="frequency" count="1">Kogia</result>
 <result title="frequency" count="1">Andro</result>
 <result title="frequency" count="1">Allosaurus</result>
 <result title="frequency" count="1">Forest</result>
 <result title="frequency" count="1">Ciona</result>
 <result title="frequency" count="1">Morus</result>
</results>
